V2Mp3/__init__.py
V2Mp3/main.pyw
V2Mp3/appEvents/__init__.py
V2Mp3/appEvents/events.py
V2Mp3/appGUI/__init__.py
V2Mp3/appGUI/layout.py
V2Mp3/appLogger/__init__.py
V2Mp3/appLogger/appLogger.py
V2Mp3/downloads/audio/.gitkeep
V2Mp3/downloads/videos/.gitkeep
V2Mp3/logs/.gitkeep
V2Mp3-0.2.0.dist-info/LICENSE
V2Mp3-0.2.0.dist-info/METADATA
V2Mp3-0.2.0.dist-info/WHEEL
V2Mp3-0.2.0.dist-info/entry_points.txt
V2Mp3-0.2.0.dist-info/top_level.txt
V2Mp3-0.2.0.dist-info/RECORD
