Metadata-Version: 2.1
Name: V2Mp3
Version: 0.2.0
Summary: Compact video-to-audio conversion tool with built-in YouTube video/audio download functionality.
Home-page: https://github.com/schlopp96/V2Mp3
Author: schlopp96
Author-email: schloppdaddy@gmail.com
License: UNKNOWN
Keywords: youtube,to,mp3,video,file,convert,converter,download,python,py,python3,audio,conversion,gui,mp4,avi,mpeg,format
Platform: UNKNOWN
Classifier: Development Status :: 3 - Alpha
Classifier: Intended Audience :: Education
Classifier: Intended Audience :: End Users/Desktop
Classifier: License :: OSI Approved :: GNU General Public License v3 (GPLv3)
Classifier: Natural Language :: English
Classifier: Operating System :: Microsoft :: Windows
Classifier: Programming Language :: Python :: 3
Classifier: Programming Language :: Python :: 3.9
Classifier: Programming Language :: Python :: 3.10
Classifier: Topic :: Multimedia
Classifier: Topic :: Multimedia :: Sound/Audio
Classifier: Topic :: Multimedia :: Sound/Audio :: Conversion
Classifier: Topic :: Multimedia :: Video
Classifier: Topic :: Multimedia :: Video :: Conversion
Classifier: Topic :: Utilities
License-File: LICENSE
Requires-Dist: moviepy (>=1.0.3)
Requires-Dist: PySimpleGUI (>=4.59.0)
Requires-Dist: pytube (>=12.0.0)
Requires-Dist: setuptools (>=58.1.0)
